fastz/__init__.py
fastz/core.py
fastz/plotting.py
fastz-1.0.0.dist-info/LICENSE
fastz-1.0.0.dist-info/METADATA
fastz-1.0.0.dist-info/WHEEL
fastz-1.0.0.dist-info/top_level.txt
fastz-1.0.0.dist-info/RECORD
