Metadata-Version: 2.1
Name: fastz
Version: 1.0.0
Summary: Lumped-element impedance calculator and frequency-domain plotter.
Home-page: https://github.com/whileman133/fastz
Author: Wesley Hileman
Author-email: wh@bench7.org
Project-URL: Bug Tracker, https://github.com/whileman133/fastz/issues
Classifier: Programming Language :: Python :: 3
Classifier: License :: OSI Approved :: MIT License
Classifier: Operating System :: OS Independent
Requires-Python: >=3.6
License-File: LICENSE
Requires-Dist: numpy >=1.15
Requires-Dist: matplotlib >=3.1
Provides-Extra: dev
Requires-Dist: pytest >=5.2 ; extra == 'dev'
Provides-Extra: doc
Requires-Dist: jupyterlab >=3.0 ; extra == 'doc'
